{ "columns":39,
 "image":"Image\/tiles-8.png",
 "imageheight":515,
 "imagewidth":669,
 "margin":1,
 "name":"tiles-8",
 "spacing":1,
 "tilecount":1170,
 "tiledversion":"1.11.2",
 "tileheight":16,
 "tiles":[
        {
         "id":0,
         "properties":[
                {
                 "name":"Type",
                 "type":"string",
                 "value":"SolidBlock"
                }]
        }, 
        {
         "id":1,
         "properties":[
                {
                 "name":"Type",
                 "type":"string",
                 "value":"SolidBlock"
                }]
        }, 
        {
         "id":2,
         "properties":[
                {
                 "name":"Type",
                 "type":"string",
                 "value":"SolidBlock"
                }]
        }, 
        {
         "id":4,
         "properties":[
                {
                 "name":"Type",
                 "type":"string",
                 "value":"SolidBlock"
                }]
        }, 
        {
         "id":5,
         "properties":[
                {
                 "name":"Type",
                 "type":"string",
                 "value":"SolidBlock"
                }]
        }, 
        {
         "id":6,
         "properties":[
                {
                 "name":"Type",
                 "type":"string",
                 "value":"SolidBlock"
                }]
        }, 
        {
         "id":8,
         "properties":[
                {
                 "name":"Type",
                 "type":"string",
                 "value":"SolidBlock"
                }]
        }, 
        {
         "id":9,
         "properties":[
                {
                 "name":"Type",
                 "type":"string",
                 "value":"SolidBlock"
                }]
        }, 
        {
         "id":10,
         "properties":[
                {
                 "name":"Type",
                 "type":"string",
                 "value":"SolidBlock"
                }]
        }, 
        {
         "id":39,
         "properties":[
                {
                 "name":"Type",
                 "type":"string",
                 "value":"SolidBlock"
                }]
        }, 
        {
         "id":40,
         "properties":[
                {
                 "name":"Type",
                 "type":"string",
                 "value":"SolidBlock"
                }]
        }, 
        {
         "id":41,
         "properties":[
                {
                 "name":"Type",
                 "type":"string",
                 "value":"SolidBlock"
                }]
        }, 
        {
         "id":43,
         "properties":[
                {
                 "name":"Type",
                 "type":"string",
                 "value":"SolidBlock"
                }]
        }, 
        {
         "id":44,
         "properties":[
                {
                 "name":"Type",
                 "type":"string",
                 "value":"SolidBlock"
                }]
        }, 
        {
         "id":45,
         "properties":[
                {
                 "name":"Type",
                 "type":"string",
                 "value":"SolidBlock"
                }]
        }, 
        {
         "id":47,
         "properties":[
                {
                 "name":"Type",
                 "type":"string",
                 "value":"SolidBlock"
                }]
        }, 
        {
         "id":48,
         "properties":[
                {
                 "name":"Type",
                 "type":"string",
                 "value":"SolidBlock"
                }]
        }, 
        {
         "id":49,
         "properties":[
                {
                 "name":"Type",
                 "type":"string",
                 "value":"SolidBlock"
                }]
        }, 
        {
         "id":117,
         "properties":[
                {
                 "name":"Type",
                 "type":"string",
                 "value":"Question"
                }]
        }, 
        {
         "id":120,
         "properties":[
                {
                 "name":"Type",
                 "type":"string",
                 "value":"Coin"
                }]
        }, 
        {
         "id":123,
         "properties":[
                {
                 "name":"Type",
                 "type":"string",
                 "value":"SolidBlock"
                }]
        }, 
        {
         "id":124,
         "properties":[
                {
                 "name":"Type",
                 "type":"string",
                 "value":"SolidBlock"
                }]
        }, 
        {
         "id":128,
         "properties":[
                {
                 "name":"Type",
                 "type":"string",
                 "value":"SolidBlock"
                }]
        }, 
        {
         "id":129,
         "properties":[
                {
                 "name":"Type",
                 "type":"string",
                 "value":"SolidBlock"
                }]
        }, 
        {
         "id":162,
         "properties":[
                {
                 "name":"Type",
                 "type":"string",
                 "value":"SolidBlock"
                }]
        }, 
        {
         "id":163,
         "properties":[
                {
                 "name":"Type",
                 "type":"string",
                 "value":"SolidBlock"
                }]
        }, 
        {
         "id":167,
         "properties":[
                {
                 "name":"Type",
                 "type":"string",
                 "value":"SolidBlock"
                }]
        }, 
        {
         "id":168,
         "properties":[
                {
                 "name":"Type",
                 "type":"string",
                 "value":"SolidBlock"
                }]
        }, 
        {
         "id":195,
         "properties":[
                {
                 "name":"Type",
                 "type":"string",
                 "value":"BrickBlock"
                }]
        }, 
        {
         "id":197,
         "properties":[
                {
                 "name":"Type",
                 "type":"string",
                 "value":"BrickBlock"
                }]
        }, 
        {
         "id":199,
         "properties":[
                {
                 "name":"Type",
                 "type":"string",
                 "value":"BrickBlock"
                }]
        }, 
        {
         "id":351,
         "properties":[
                {
                 "name":"Type",
                 "type":"string",
                 "value":"SolidBlock"
                }]
        }, 
        {
         "id":352,
         "properties":[
                {
                 "name":"Type",
                 "type":"string",
                 "value":"SolidBlock"
                }]
        }, 
        {
         "id":353,
         "properties":[
                {
                 "name":"Type",
                 "type":"string",
                 "value":"SolidBlock"
                }]
        }, 
        {
         "id":390,
         "properties":[
                {
                 "name":"Type",
                 "type":"string",
                 "value":"FlagEnemy"
                }]
        }, 
        {
         "id":429,
         "properties":[
                {
                 "name":"Type",
                 "type":"string",
                 "value":"FlagWin"
                }]
        }, 
        {
         "id":780,
         "properties":[
                {
                 "name":"Type",
                 "type":"string",
                 "value":"FlagCastle"
                }]
        }],
 "tilewidth":16,
 "type":"tileset",
 "version":"1.10"
}